image_processing_toolkit/__init__.py
image_processing_toolkit/analysis.py
image_processing_toolkit/feature_extraction.py
image_processing_toolkit/filtering.py
image_processing_toolkit/io.py
image_processing_toolkit/transformations.py
image_processing_toolkit-0.1.0.dist-info/METADATA
image_processing_toolkit-0.1.0.dist-info/WHEEL
image_processing_toolkit-0.1.0.dist-info/RECORD
